setup.py
django_zencoder.egg-info/PKG-INFO
django_zencoder.egg-info/SOURCES.txt
django_zencoder.egg-info/dependency_links.txt
django_zencoder.egg-info/pbr.json
django_zencoder.egg-info/requires.txt
django_zencoder.egg-info/top_level.txt
zencoder/__init__.py
zencoder/models.py
zencoder/serializers.py
zencoder/tests.py
zencoder/urls.py
zencoder/views.py
zencoder/__pycache__/__init__.cpython-32.pyc
zencoder/__pycache__/__init__.cpython-34.pyc
zencoder/__pycache__/models.cpython-32.pyc
zencoder/__pycache__/models.cpython-34.pyc
zencoder/__pycache__/serializers.cpython-34.pyc
zencoder/__pycache__/urls.cpython-34.pyc
zencoder/__pycache__/views.cpython-34.pyc
zencoder/conf/__init__.py
zencoder/conf/defaults.py
zencoder/conf/__pycache__/__init__.cpython-34.pyc
zencoder/conf/__pycache__/defaults.cpython-34.pyc
zencoder/management/__init__.py
zencoder/management/__pycache__/__init__.cpython-34.pyc
zencoder/management/commands/__init__.py
zencoder/management/commands/get-durations.py
zencoder/migrations/0001_initial.py
zencoder/migrations/0002_add_video_duration.py
zencoder/migrations/__init__.py
zencoder/migrations/__pycache__/0001_initial.cpython-34.pyc
zencoder/migrations/__pycache__/0002_add_video_duration.cpython-34.pyc
zencoder/migrations/__pycache__/__init__.cpython-34.pyc
zencoder/south_migrations/0001_initial.py
zencoder/south_migrations/__init__.py
zencoder/templates/zencoder/embed/default.html
zencoder/templates/zencoder/embed/encoding.html
zencoder/templates/zencoder/embed/failed.html
zencoder/utils/__init__.py
zencoder/utils/serializers.py
zencoder/utils/__pycache__/__init__.cpython-34.pyc
zencoder/utils/__pycache__/fields.cpython-34.pyc
zencoder/utils/__pycache__/serializers.cpython-34.pyc