Metadata-Version: 1.0
Name: django-zencoder
Version: 0.2.69
Summary: A Django app that allows the upload and encoding of videos with Zencoder
Home-page: https://github.com/theonion/django-zencoder
Author: Onion Tech Team
Author-email: tech@theonion.com
License: MIT
Platform: UNKNOWN
